xparser-0.0.4.dist-info/DESCRIPTION.rst
xparser-0.0.4.dist-info/METADATA
xparser-0.0.4.dist-info/RECORD
xparser-0.0.4.dist-info/WHEEL
xparser-0.0.4.dist-info/metadata.json
xparser-0.0.4.dist-info/top_level.txt
xrp/__init__.py
xrp/__version__.py
xrp/match.py
xrp/parser.py
xrp/views.py
